Metadata-Version: 1.1
Name: compare-requirements
Version: 0.2.2
Summary: Package description
